dynamic_form/__init__.py
dynamic_form/datastore_mongodb.py
dynamic_form/errors.py
dynamic_form/form_manager.py
dynamic_form/interfaces.py
dynamic_form/parser_json.py
dynamic_form/template_builder.py
test/__init__.py
test/test_datastore_mongo.py
test/test_form_manager.py
test/test_json_parser.py
test/test_main.py
test/test_utils.py
dynamic_form-0.3.1.dist-info/LICENCE
dynamic_form-0.3.1.dist-info/METADATA
dynamic_form-0.3.1.dist-info/WHEEL
dynamic_form-0.3.1.dist-info/top_level.txt
dynamic_form-0.3.1.dist-info/RECORD
