Metadata-Version: 2.1
Name: dynamic-form
Version: 0.3.1
Summary: A package to dynamically load webforms from a data store (i.e. database) during runtime
Home-page: https://github.com/bedapub/dynamic-form
Author: Rafael S. Müller
Author-email: rafa.molitoris@gmail.com
License: UNKNOWN
Project-URL: Documentation, https://dynamic-form.readthedocs.io/en/stable/
Project-URL: Code, https://github.com/bedapub/dynamic-form
Keywords: form webform database datastore
Platform: UNKNOWN
Classifier: Intended Audience :: Developers
Classifier: License :: OSI Approved :: GNU Lesser General Public License v3 (LGPLv3)
Classifier: Operating System :: OS Independent
Classifier: Programming Language :: Python :: 3.7
Requires-Dist: pymongo (>=3.10.1)
Requires-Dist: wtforms (>=2.2.1)
Requires-Dist: flask-wtf (>=0.14.2)
Requires-Dist: expiringdict (>=1.2.0)
